rtflite/__init__.py
rtflite/assemble.py
rtflite/attributes.py
rtflite/convert.py
rtflite/encode.py
rtflite/figure.py
rtflite/fonts_mapping.py
rtflite/input.py
rtflite/row.py
rtflite/strwidth.py
rtflite/type_guards.py
rtflite/core/__init__.py
rtflite/core/config.py
rtflite/core/constants.py
rtflite/data/HAMD17.parquet
rtflite/data/__init__.py
rtflite/data/adae.parquet
rtflite/data/adsl.parquet
rtflite/data/baseline.parquet
rtflite/data/tbl1.parquet
rtflite/data/tbl2.parquet
rtflite/data/tbl3.parquet
rtflite/dictionary/__init__.py
rtflite/dictionary/color_table.py
rtflite/dictionary/libreoffice.py
rtflite/dictionary/unicode_latex.py
rtflite/encoding/__init__.py
rtflite/encoding/base.py
rtflite/encoding/engine.py
rtflite/encoding/renderer.py
rtflite/encoding/unified_encoder.py
rtflite/fonts/README.md
rtflite/fonts/__init__.py
rtflite/fonts/cros/Caladea-Regular.ttf
rtflite/fonts/cros/Carlito-Regular.ttf
rtflite/fonts/cros/Gelasio-Regular.ttf
rtflite/fonts/liberation/LiberationMono-Regular.ttf
rtflite/fonts/liberation/LiberationSans-Regular.ttf
rtflite/fonts/liberation/LiberationSerif-Regular.ttf
rtflite/pagination/__init__.py
rtflite/pagination/core.py
rtflite/pagination/processor.py
rtflite/pagination/strategies/__init__.py
rtflite/pagination/strategies/base.py
rtflite/pagination/strategies/defaults.py
rtflite/pagination/strategies/grouping.py
rtflite/pagination/strategies/registry.py
rtflite/rtf/__init__.py
rtflite/rtf/syntax.py
rtflite/services/__init__.py
rtflite/services/color_service.py
rtflite/services/document_service.py
rtflite/services/encoding_service.py
rtflite/services/figure_service.py
rtflite/services/grouping_service.py
rtflite/services/text_conversion_service.py
rtflite/text_conversion/__init__.py
rtflite/text_conversion/converter.py
rtflite/text_conversion/symbols.py
rtflite-2.5.3.dist-info/METADATA
rtflite-2.5.3.dist-info/WHEEL
rtflite-2.5.3.dist-info/licenses/LICENSE
rtflite-2.5.3.dist-info/licenses/LICENSES_THIRD_PARTY
rtflite-2.5.3.dist-info/RECORD
