Metadata-Version: 2.4
Name: rtflite
Version: 2.5.3
Summary: Lightweight RTF composer for Python
Project-URL: Homepage, https://pharmaverse.github.io/rtflite/
Project-URL: Documentation, https://pharmaverse.github.io/rtflite/
Project-URL: Repository, https://github.com/pharmaverse/rtflite
Project-URL: Issues, https://github.com/pharmaverse/rtflite/issues
Project-URL: Changelog, https://github.com/pharmaverse/rtflite/blob/main/CHANGELOG.md
Author-email: Yilong Zhang <elong0527@gmail.com>, Nan Xiao <me@nanx.me>
License-File: LICENSE
License-File: LICENSES_THIRD_PARTY
Classifier: Development Status :: 3 - Alpha
Classifier: Intended Audience :: Developers
Classifier: Intended Audience :: Healthcare Industry
Classifier: Intended Audience :: Information Technology
Classifier: Intended Audience :: Science/Research
Classifier: License :: OSI Approved :: MIT License
Classifier: Programming Language :: Python :: 3
Classifier: Programming Language :: Python :: 3.10
Classifier: Programming Language :: Python :: 3.11
Classifier: Programming Language :: Python :: 3.12
Classifier: Programming Language :: Python :: 3.13
Classifier: Programming Language :: Python :: 3.14
Classifier: Topic :: Office/Business :: Office Suites
Classifier: Topic :: Text Processing
Requires-Python: >=3.10
Requires-Dist: narwhals>=1.0.0
Requires-Dist: pillow>=8.0.0
Requires-Dist: polars>=1.0.0
Requires-Dist: pydantic>=2.0.0
Provides-Extra: docx
Requires-Dist: python-docx>=1.0.0; extra == 'docx'
Provides-Extra: pdf
Requires-Dist: pypdf>=5.0.0; extra == 'pdf'
